topsis/__init__.py
topsis/__main__.py
topsis/topsis.py
topsis_kenpreet_102303365-1.0.2.dist-info/METADATA
topsis_kenpreet_102303365-1.0.2.dist-info/WHEEL
topsis_kenpreet_102303365-1.0.2.dist-info/entry_points.txt
topsis_kenpreet_102303365-1.0.2.dist-info/top_level.txt
topsis_kenpreet_102303365-1.0.2.dist-info/RECORD
