Metadata-Version: 2.4
Name: topsis-kenpreet-102303365
Version: 1.0.2
Summary: TOPSIS implementation using Python
Author: Kenpreet Singh Thukral
Requires-Dist: pandas
Requires-Dist: numpy
Dynamic: author
Dynamic: description
Dynamic: description-content-type
Dynamic: requires-dist
Dynamic: summary
